appclassdoc/__init__.py
appclassdoc/appclassdoc.py
appclassdoc/resources/index.html
appclassdoc/resources/script.js
appclassdoc/resources/start-page.html
appclassdoc/resources/stylesheet.css
appclassdoc/resources/fonts/DejaVuSans-Bold-webfont.eot
appclassdoc/resources/fonts/DejaVuSans-Bold-webfont.svg
appclassdoc/resources/fonts/DejaVuSans-Bold-webfont.ttf
appclassdoc/resources/fonts/DejaVuSans-Bold-webfont.woff
appclassdoc/resources/fonts/DejaVuSans-BoldOblique-webfont.eot
appclassdoc/resources/fonts/DejaVuSans-BoldOblique-webfont.svg
appclassdoc/resources/fonts/DejaVuSans-BoldOblique-webfont.ttf
appclassdoc/resources/fonts/DejaVuSans-BoldOblique-webfont.woff
appclassdoc/resources/fonts/DejaVuSans-Oblique-webfont.eot
appclassdoc/resources/fonts/DejaVuSans-Oblique-webfont.svg
appclassdoc/resources/fonts/DejaVuSans-Oblique-webfont.ttf
appclassdoc/resources/fonts/DejaVuSans-Oblique-webfont.woff
appclassdoc/resources/fonts/DejaVuSans-webfont.eot
appclassdoc/resources/fonts/DejaVuSans-webfont.svg
appclassdoc/resources/fonts/DejaVuSans-webfont.ttf
appclassdoc/resources/fonts/DejaVuSans-webfont.woff
appclassdoc/resources/fonts/DejaVuSansCondensed-Bold-webfont.eot
appclassdoc/resources/fonts/DejaVuSansCondensed-Bold-webfont.svg
appclassdoc/resources/fonts/DejaVuSansCondensed-Bold-webfont.ttf
appclassdoc/resources/fonts/DejaVuSansCondensed-Bold-webfont.woff
appclassdoc/resources/fonts/DejaVuSansCondensed-BoldOblique-webfont.eot
appclassdoc/resources/fonts/DejaVuSansCondensed-BoldOblique-webfont.svg
appclassdoc/resources/fonts/DejaVuSansCondensed-BoldOblique-webfont.ttf
appclassdoc/resources/fonts/DejaVuSansCondensed-BoldOblique-webfont.woff
appclassdoc/resources/fonts/DejaVuSansCondensed-Oblique-webfont.eot
appclassdoc/resources/fonts/DejaVuSansCondensed-Oblique-webfont.svg
appclassdoc/resources/fonts/DejaVuSansCondensed-Oblique-webfont.ttf
appclassdoc/resources/fonts/DejaVuSansCondensed-Oblique-webfont.woff
appclassdoc/resources/fonts/DejaVuSansCondensed-webfont.eot
appclassdoc-1.0.1.dist-info/LICENSE.txt
appclassdoc-1.0.1.dist-info/METADATA
appclassdoc-1.0.1.dist-info/WHEEL
appclassdoc-1.0.1.dist-info/entry_points.txt
appclassdoc-1.0.1.dist-info/top_level.txt
appclassdoc-1.0.1.dist-info/RECORD
