Metadata-Version: 2.1
Name: appclassdoc
Version: 1.0.1
Summary: A package to create a Javadoc-like API documentation site for PeopleSoft Application Classes
Home-page: https://github.com/lbaca/appclassdoc
Author: Leandro Baca
Author-email: leandrobaca77@gmail.com
License: UNKNOWN
Keywords: peoplesoft peoplecode application-class application-package documentation api appclassdoc javadoc
Platform: UNKNOWN
Classifier: Development Status :: 5 - Production/Stable
Classifier: Environment :: Console
Classifier: Intended Audience :: Developers
Classifier: Intended Audience :: Information Technology
Classifier: Programming Language :: Python :: 3
Classifier: Programming Language :: Python :: 3.6
Classifier: Programming Language :: Python :: 3.7
Classifier: Programming Language :: Python :: 3.8
Classifier: Programming Language :: Python :: 3.9
Classifier: License :: OSI Approved :: MIT License
Classifier: Operating System :: OS Independent
Classifier: Topic :: Documentation
Classifier: Topic :: Software Development :: Documentation
Requires-Python: ~=3.6
Requires-Dist: lxml
Requires-Dist: peoplecodeparser
